simpleblog/__init__.py
simpleblog/apps.py
simpleblog/blocks.py
simpleblog/models.py
simpleblog/settings.py
simpleblog/utils.py
simpleblog/version.py
simpleblog/views.py
simpleblog/management/__init__.py
simpleblog/management/commands/__init__.py
simpleblog/management/commands/createblogadmin.py
simpleblog/migrations/0001_initial.py
simpleblog/migrations/0002_auto_20211224_1123.py
simpleblog/migrations/0003_auto_20211224_1623.py
simpleblog/migrations/0004_auto_20211225_1732.py
simpleblog/migrations/0005_index_content.py
simpleblog/migrations/0006_remove_index_streamblocks.py
simpleblog/migrations/__init__.py
simpleblog/static/simpleblog/css/blog.css
simpleblog/static/simpleblog/css/bootstrap.min.css
simpleblog/static/simpleblog/css/github.min.css
simpleblog/static/simpleblog/css/lightgallery-transitions.min.css
simpleblog/static/simpleblog/css/lightgallery.min.css
simpleblog/static/simpleblog/fonts/lg.svg
simpleblog/static/simpleblog/fonts/lg.ttf
simpleblog/static/simpleblog/fonts/lg.woff
simpleblog/static/simpleblog/fonts/materialdesignicons-webfont.eot
simpleblog/static/simpleblog/fonts/materialdesignicons-webfont.ttf
simpleblog/static/simpleblog/fonts/materialdesignicons-webfont.woff
simpleblog/static/simpleblog/fonts/materialdesignicons-webfont.woff2
simpleblog/static/simpleblog/img/loading.gif
simpleblog/static/simpleblog/img/video-play.png
simpleblog/static/simpleblog/img/vimeo-play.png
simpleblog/static/simpleblog/img/youtube-play.png
simpleblog/static/simpleblog/js/blog.js
simpleblog/static/simpleblog/js/bootstrap.min.js
simpleblog/static/simpleblog/js/plugins/gist.min.js
simpleblog/static/simpleblog/js/plugins/gist.min.js:Zone.Identifier
simpleblog/static/simpleblog/js/plugins/highlight.min.js
simpleblog/static/simpleblog/js/plugins/lightgallery.min.js
simpleblog/static/simpleblog/js/plugins/mermaid.min.js
simpleblog/static/simpleblog/js/plugins/mermaid.min.js:Zone.Identifier
simpleblog/templates/base.html
wagtail_simple_blog-0.0.3.dist-info/LICENSE
wagtail_simple_blog-0.0.3.dist-info/METADATA
wagtail_simple_blog-0.0.3.dist-info/WHEEL
wagtail_simple_blog-0.0.3.dist-info/top_level.txt
wagtail_simple_blog-0.0.3.dist-info/RECORD
